blobcli/__init__.py
blobcli/cli.py
blobcli/client.py
blobcli-0.0.6.dist-info/LICENSE
blobcli-0.0.6.dist-info/METADATA
blobcli-0.0.6.dist-info/WHEEL
blobcli-0.0.6.dist-info/entry_points.txt
blobcli-0.0.6.dist-info/top_level.txt
blobcli-0.0.6.dist-info/RECORD
