Metadata-Version: 2.1
Name: blobcli
Version: 0.0.6
Summary: This is a command line interface for easy operation with blobs in Azure Blob Storage.
Home-page: https://github.com/rnakamine/blobcli
Author: Ryo Nakamine
Author-email: rnakamine8080@gmail.com
License: UNKNOWN
Platform: UNKNOWN
Classifier: Development Status :: 4 - Beta
Classifier: License :: OSI Approved :: MIT License
Classifier: Programming Language :: Python :: 3
Classifier: Programming Language :: Python :: 3.6
Classifier: Programming Language :: Python :: 3.7
Classifier: Programming Language :: Python :: 3.8
Classifier: Operating System :: OS Independent
Requires-Python: ~=3.6
Requires-Dist: Click
Requires-Dist: azure-storage-blob (==12.8.0)
